byzpy/__init__.py
byzpy/_dependencies.py
byzpy/cli.py
byzpy/py.typed
byzpy/aggregators/__init__.py
byzpy/aggregators/_chunking.py
byzpy/aggregators/base.py
byzpy/aggregators/coordinate_wise/__init__.py
byzpy/aggregators/coordinate_wise/_tiling.py
byzpy/aggregators/coordinate_wise/mean_of_medians.py
byzpy/aggregators/coordinate_wise/median.py
byzpy/aggregators/coordinate_wise/trimmed_mean.py
byzpy/aggregators/coordinate_wise/tests/__init__.py
byzpy/aggregators/coordinate_wise/tests/test_mean_of_medians.py
byzpy/aggregators/coordinate_wise/tests/test_median.py
byzpy/aggregators/coordinate_wise/tests/test_trmean.py
byzpy/aggregators/geometric_wise/__init__.py
byzpy/aggregators/geometric_wise/geometric_median.py
byzpy/aggregators/geometric_wise/krum.py
byzpy/aggregators/geometric_wise/minimum_diameter_average.py
byzpy/aggregators/geometric_wise/monna.py
byzpy/aggregators/geometric_wise/smea.py
byzpy/aggregators/geometric_wise/tests/__init__.py
byzpy/aggregators/geometric_wise/tests/test_geometric_median.py
byzpy/aggregators/geometric_wise/tests/test_krum.py
byzpy/aggregators/geometric_wise/tests/test_minimum_diameter_average.py
byzpy/aggregators/geometric_wise/tests/test_monna.py
byzpy/aggregators/geometric_wise/tests/test_smea.py
byzpy/aggregators/norm_wise/__init__.py
byzpy/aggregators/norm_wise/caf.py
byzpy/aggregators/norm_wise/center_clipping.py
byzpy/aggregators/norm_wise/comparative_gradient_elimination.py
byzpy/aggregators/norm_wise/tests/__init__.py
byzpy/aggregators/norm_wise/tests/test_caf.py
byzpy/aggregators/norm_wise/tests/test_center_clipping.py
byzpy/aggregators/norm_wise/tests/test_comparative_gradient_elimination.py
byzpy/aggregators/tests/test_chunking.py
byzpy/attacks/__init__.py
byzpy/attacks/base.py
byzpy/attacks/empire.py
byzpy/attacks/gaussian.py
byzpy/attacks/inf.py
byzpy/attacks/label_flip.py
byzpy/attacks/little.py
byzpy/attacks/mimic.py
byzpy/attacks/sign_flip.py
byzpy/attacks/tests/__init__.py
byzpy/attacks/tests/test_empire_attack.py
byzpy-0.1.3.dist-info/LICENSE
byzpy-0.1.3.dist-info/METADATA
byzpy-0.1.3.dist-info/WHEEL
byzpy-0.1.3.dist-info/entry_points.txt
byzpy-0.1.3.dist-info/top_level.txt
byzpy-0.1.3.dist-info/RECORD
